crs/__init__.py
crs/crs.py
crs/version.txt
crs-0.1.1.dist-info/DESCRIPTION.rst
crs-0.1.1.dist-info/METADATA
crs-0.1.1.dist-info/RECORD
crs-0.1.1.dist-info/WHEEL
crs-0.1.1.dist-info/metadata.json
crs-0.1.1.dist-info/top_level.txt
