Metadata-Version: 2.0
Name: crs
Version: 0.1.1
Summary: Geographic Coordinate Reference System Encapsulation and Conversion
Home-page: http://github.com/gregory-halverson/crs
Author: Gregory Halverson
Author-email: gregory.halverson@gmail.com
License: MIT
Keywords: geography coordinates projections
Platform: UNKNOWN
Classifier: Development Status :: 3 - Alpha
Classifier: Intended Audience :: Developers
Classifier: Topic :: Software Development :: Build Tools
Classifier: License :: OSI Approved :: MIT License
Classifier: Programming Language :: Python :: 2
Classifier: Programming Language :: Python :: 2.6
Classifier: Programming Language :: Python :: 2.7
Classifier: Programming Language :: Python :: 3
Classifier: Programming Language :: Python :: 3.2
Classifier: Programming Language :: Python :: 3.3
Classifier: Programming Language :: Python :: 3.4
Requires-Dist: gdal
Requires-Dist: pyproj
Requires-Dist: six
